XStatic_jquery_ui-1.13.0.1-py3.13-nspkg.pth
xstatic/pkg/jquery_ui/__init__.py
xstatic/pkg/jquery_ui/data/jquery-ui.css
xstatic/pkg/jquery_ui/data/jquery-ui.js
xstatic/pkg/jquery_ui/data/jquery-ui.min.css
xstatic/pkg/jquery_ui/data/jquery-ui.min.js
xstatic/pkg/jquery_ui/data/jquery-ui.structure.css
xstatic/pkg/jquery_ui/data/jquery-ui.structure.min.css
xstatic/pkg/jquery_ui/data/jquery-ui.theme.css
xstatic/pkg/jquery_ui/data/jquery-ui.theme.min.css
xstatic/pkg/jquery_ui/data/images/ui-bg_diagonals-thick_18_b81900_40x40.png
xstatic/pkg/jquery_ui/data/images/ui-bg_diagonals-thick_20_666666_40x40.png
xstatic/pkg/jquery_ui/data/images/ui-bg_glass_100_f6f6f6_1x400.png
xstatic/pkg/jquery_ui/data/images/ui-bg_glass_100_fdf5ce_1x400.png
xstatic/pkg/jquery_ui/data/images/ui-bg_glass_65_ffffff_1x400.png
xstatic/pkg/jquery_ui/data/images/ui-bg_gloss-wave_35_f6a828_500x100.png
xstatic/pkg/jquery_ui/data/images/ui-bg_highlight-soft_100_eeeeee_1x100.png
xstatic/pkg/jquery_ui/data/images/ui-bg_highlight-soft_75_ffe45c_1x100.png
xstatic/pkg/jquery_ui/data/images/ui-icons_222222_256x240.png
xstatic/pkg/jquery_ui/data/images/ui-icons_228ef1_256x240.png
xstatic/pkg/jquery_ui/data/images/ui-icons_444444_256x240.png
xstatic/pkg/jquery_ui/data/images/ui-icons_555555_256x240.png
xstatic/pkg/jquery_ui/data/images/ui-icons_777620_256x240.png
xstatic/pkg/jquery_ui/data/images/ui-icons_777777_256x240.png
xstatic/pkg/jquery_ui/data/images/ui-icons_cc0000_256x240.png
xstatic/pkg/jquery_ui/data/images/ui-icons_ef8c08_256x240.png
xstatic/pkg/jquery_ui/data/images/ui-icons_ffd27a_256x240.png
xstatic/pkg/jquery_ui/data/images/ui-icons_ffffff_256x240.png
xstatic/pkg/jquery_ui/data/themes/base/jquery-ui.css
xstatic/pkg/jquery_ui/data/themes/base/jquery-ui.min.css
xstatic/pkg/jquery_ui/data/themes/base/theme.css
xstatic/pkg/jquery_ui/data/themes/base/images/ui-icons_444444_256x240.png
xstatic/pkg/jquery_ui/data/themes/base/images/ui-icons_555555_256x240.png
xstatic_jquery_ui-1.13.0.1.dist-info/METADATA
xstatic_jquery_ui-1.13.0.1.dist-info/WHEEL
xstatic_jquery_ui-1.13.0.1.dist-info/namespace_packages.txt
xstatic_jquery_ui-1.13.0.1.dist-info/top_level.txt
xstatic_jquery_ui-1.13.0.1.dist-info/RECORD
