Metadata-Version: 2.4
Name: XStatic-jquery-ui
Version: 1.13.0.1
Summary: jquery-ui 1.13.0 (XStatic packaging standard)
Home-page: http://jqueryui.com/
Maintainer: Thomas Waldmann
Maintainer-email: tw@waldmann-edv.de
License: (same as jquery-ui)
Keywords: jquery_ui xstatic
Platform: any
Requires-Dist: XStatic-jQuery
Dynamic: description
Dynamic: home-page
Dynamic: keywords
Dynamic: license
Dynamic: maintainer
Dynamic: maintainer-email
Dynamic: platform
Dynamic: requires-dist
Dynamic: summary
